inmanta_plugins/ip/__init__.py
inmanta_plugins/ip/setup.cfg
inmanta_plugins/ip/model/_init.cf
inmanta_plugins/ip/model/services.cf
inmanta_plugins/ip/templates/host_uri.j2
inmanta_module_ip-2.0.3.dist-info/METADATA
inmanta_module_ip-2.0.3.dist-info/WHEEL
inmanta_module_ip-2.0.3.dist-info/top_level.txt
inmanta_module_ip-2.0.3.dist-info/RECORD
