Metadata-Version: 2.1
Name: inmanta-module-ip
Version: 2.0.3
License: Apache 2.0
Requires-Dist: inmanta-module-net
Requires-Dist: inmanta-module-std >=5
Requires-Dist: netaddr <2,>=0.8
Requires-Dist: zipp >=3.6
